README.txt
setup.py
nitroapi/__init__.py
nitroapi/cli.py
nitroapi/nitroapi.py
nitroapi.egg-info/PKG-INFO
nitroapi.egg-info/SOURCES.txt
nitroapi.egg-info/dependency_links.txt
nitroapi.egg-info/pbr.json
nitroapi.egg-info/requires.txt
nitroapi.egg-info/top_level.txt