Metadata-Version: 1.0
Name: nitroapi
Version: 0.1.0
Summary: Minimal wrapper around the NetScaler NITRO API
Home-page: https://github.com/swill/nitroapi
Author: Will Stevens
Author-email: wstevens@cloudops.com
License: Apache Licence v2.0
Platform: UNKNOWN
